lotterybr/__init__.py
lotterybr/app_eng.py
lotterybr/app_ptbr.py
lotterybr/get_data.py
lotterybr/open_app.py
lotterybr/translate_data.py
lotterybr-1.0.5.dist-info/licenses/LICENSE
lotterybr-1.0.5.dist-info/METADATA
lotterybr-1.0.5.dist-info/WHEEL
lotterybr-1.0.5.dist-info/top_level.txt
lotterybr-1.0.5.dist-info/RECORD
